flag.py
artifact_lab_3_package_1b4d0db5-0.3.0.dist-info/LICENSE
artifact_lab_3_package_1b4d0db5-0.3.0.dist-info/METADATA
artifact_lab_3_package_1b4d0db5-0.3.0.dist-info/WHEEL
artifact_lab_3_package_1b4d0db5-0.3.0.dist-info/top_level.txt
artifact_lab_3_package_1b4d0db5-0.3.0.dist-info/RECORD
