Metadata-Version: 2.1
Name: artifact_lab_3_package_1b4d0db5
Version: 0.3.0
Summary: Leaking environment variables via HTTP requests
Author: Your Mum
Author-email: your_email@example.com
Classifier: Programming Language :: Python :: 3
Classifier: License :: OSI Approved :: MIT License
Classifier: Operating System :: OS Independent
Requires-Python: >=3.6
License-File: LICENSE
Requires-Dist: requests
